pyfnntw-0.4.1.dist-info/METADATA
pyfnntw-0.4.1.dist-info/WHEEL
pyfnntw/__init__.py
pyfnntw/pyfnntw.cpython-311-darwin.so
pyfnntw-0.4.1.dist-info/RECORD
