Metadata-Version: 2.1
Name: pyfnntw
Version: 0.4.1
Classifier: Programming Language :: Rust
Classifier: Programming Language :: Python :: Implementation :: CPython
Classifier: Programming Language :: Python :: Implementation :: PyPy
Summary: FNNTW: Fastest Nearest Neighbor (in the) West. A fast kdtree/kNN library.
Author: Cavey Cool <caveycool@gmail.com>
Author-email: Cavey Cool <caveycool@gmail.com>
License: MIT OR Apache-2.0
Requires-Python: >=3.7
Project-URL: Source Code, https://github.com/cavemanloverboy/fnntw
